discordRebot/__init__.py
discordRebot/__main__.py
discordRebot/converter.py
discordRebot/manager.py
discordRebot/members.py
discordRebot/tryrebot.py
discord_rebot-0.0.2.dist-info/WHEEL
discord_rebot-0.0.2.dist-info/METADATA
discord_rebot-0.0.2.dist-info/RECORD
