Metadata-Version: 2.1
Name: discord-rebot
Version: 0.0.2
Summary: RegEx based command mapping discord BOT framework with authorization
Home-page: https://github.com/nkpro2000sr/discord-rebot
License: MIT
Keywords: discord,rebot,regex,tryrebot
Author: nkpro2000sr
Author-email: srnaveen2k@yahoo.com
Maintainer: nkpro2000sr
Maintainer-email: srnaveen2k@yahoo.com
Requires-Python: >=3.8,<4.0
Classifier: License :: OSI Approved :: MIT License
Classifier: Programming Language :: Python :: 3
Classifier: Programming Language :: Python :: 3.8
Requires-Dist: discord.py (>=1.3.3,<2.0.0)
Project-URL: Documentation, https://discord-rebot.readthedocs.io/en/latest/
Project-URL: Repository, https://github.com/nkpro2000sr/discord-rebot
